odoo10_addon_sentry-10.0.1.0.1-py2.7-nspkg.pth
odoo/addons/sentry/README.rst
odoo/addons/sentry/__init__.py
odoo/addons/sentry/__manifest__.py
odoo/addons/sentry/const.py
odoo/addons/sentry/logutils.py
odoo/addons/sentry/static/description/icon.png
odoo/addons/sentry/tests/__init__.py
odoo/addons/sentry/tests/test_client.py
odoo/addons/sentry/tests/test_logutils.py
odoo10_addon_sentry-10.0.1.0.1.dist-info/DESCRIPTION.rst
odoo10_addon_sentry-10.0.1.0.1.dist-info/METADATA
odoo10_addon_sentry-10.0.1.0.1.dist-info/RECORD
odoo10_addon_sentry-10.0.1.0.1.dist-info/WHEEL
odoo10_addon_sentry-10.0.1.0.1.dist-info/metadata.json
odoo10_addon_sentry-10.0.1.0.1.dist-info/namespace_packages.txt
odoo10_addon_sentry-10.0.1.0.1.dist-info/top_level.txt
